LunaDB/__init__.py
LunaDB/db.py
LunaDB/table.py
LunaDB/exceptions/__init__.py
LunaDB/exceptions/exceptions.py
LunaDB-0.5.2.dist-info/LICENSE
LunaDB-0.5.2.dist-info/METADATA
LunaDB-0.5.2.dist-info/WHEEL
LunaDB-0.5.2.dist-info/top_level.txt
LunaDB-0.5.2.dist-info/RECORD
