Metadata-Version: 2.1
Name: LunaDB
Version: 0.5.2
Summary: Lightweight file based NoSQL DB
Home-page: https://github.com/swip3798/LunaDB
Author: Christian Schweigel
Author-email: 
License: UNKNOWN
Platform: UNKNOWN
Classifier: Programming Language :: Python :: 3
Classifier: Programming Language :: Python :: 3 :: Only
Classifier: Topic :: Database
Classifier: License :: OSI Approved :: GNU Lesser General Public License v3 (LGPLv3)
Classifier: Operating System :: OS Independent
Classifier: Development Status :: 3 - Alpha
